{
  "source": "https://m-1.15min.lt/grojarastis/",
  "count": 238,
  "songs": [
    {
      "radioStation": "M1",
      "time": "15:27",
      "pageDate": "balandžio 7d.",
      "title": "Ciao Adios",
      "artist": "ANNE-MARIE",
      "playCount": 1,
      "spotifyArtistName": "",
      "spotifyTrackName": "",
      "spotifyUri": ""
    },
    {
      "radioStation": "M1",
      "time": "15:25",
      "pageDate": "balandžio 7d.",
      "title": "Nakti Sauleje",
      "artist": "SILVESTER BELT",
      "playCount": 1,
      "spotifyArtistName": "",
      "spotifyTrackName": "",
      "spotifyUri": ""
    },
    {
      "radioStation": "M1",
      "time": "15:18",
      "pageDate": "balandžio 7d.",
      "title": "Let You Go",
      "artist": "DEMI LOVATO",
      "playCount": 1,
      "spotifyArtistName": "",
      "spotifyTrackName": "",
      "spotifyUri": ""
    },
    {
      "radioStation": "M1",
      "time": "15:13",
      "pageDate": "balandžio 7d.",
      "title": "Shining",
      "artist": "GABRY PONTE & ONESOLO",
      "playCount": 1,
      "spotifyArtistName": "",
      "spotifyTrackName": "",
      "spotifyUri": ""
    },
    {
      "radioStation": "M1",
      "time": "15:10",
      "pageDate": "balandžio 7d.",
      "title": "Duok Man Zenkla",
      "artist": "ATLANTA",
      "playCount": 1,
      "spotifyArtistName": "",
      "spotifyTrackName": "",
      "spotifyUri": ""
    },
    {
      "radioStation": "M1",
      "time": "15:03",
      "pageDate": "balandžio 7d.",
      "title": "Starlight (The Fame)",
      "artist": "THE SUPERMEN LOVERS & ONEREPUBLIC",
      "playCount": 1,
      "spotifyArtistName": "",
      "spotifyTrackName": "",
      "spotifyUri": ""
    },
    {
      "radioStation": "M1",
      "time": "15:00",
      "pageDate": "balandžio 7d.",
      "title": "Tuesday",
      "artist": "BURAK YETER feat. DANELLE SANDOVAL",
      "playCount": 1,
      "spotifyArtistName": "",
      "spotifyTrackName": "",
      "spotifyUri": ""
    },
    {
      "radioStation": "M1",
      "time": "14:57",
      "pageDate": "balandžio 7d.",
      "title": "What You Want",
      "artist": "ANGELE feat. JUSTICE",
      "playCount": 1,
      "spotifyArtistName": "",
      "spotifyTrackName": "",
      "spotifyUri": ""
    },
    {
      "radioStation": "M1",
      "time": "14:50",
      "pageDate": "balandžio 7d.",
      "title": "Baigeme Mokykla (2021)",
      "artist": "MARIJONAS MIKUTAVICIUS x IGLE x KARINA",
      "playCount": 1,
      "spotifyArtistName": "",
      "spotifyTrackName": "",
      "spotifyUri": ""
    },
    {
      "radioStation": "M1",
      "time": "14:47",
      "pageDate": "balandžio 7d.",
      "title": "Catharina",
      "artist": "MARTIN GARRIX",
      "playCount": 1,
      "spotifyArtistName": "",
      "spotifyTrackName": "",
      "spotifyUri": ""
    },
    {
      "radioStation": "M1",
      "time": "14:43",
      "pageDate": "balandžio 7d.",
      "title": "Better Man Than Me",
      "artist": "MARSHMELLO X HUDSON WESTBROOK",
      "playCount": 1,
      "spotifyArtistName": "",
      "spotifyTrackName": "",
      "spotifyUri": ""
    },
    {
      "radioStation": "M1",
      "time": "14:35",
      "pageDate": "balandžio 7d.",
      "title": "Need Your Love",
      "artist": "ONEREPUBLIC",
      "playCount": 1,
      "spotifyArtistName": "",
      "spotifyTrackName": "",
      "spotifyUri": ""
    },
    {
      "radioStation": "M1",
      "time": "14:33",
      "pageDate": "balandžio 7d.",
      "title": "Menulis",
      "artist": "2KVEPAVIMAS su ADRINA",
      "playCount": 1,
      "spotifyArtistName": "",
      "spotifyTrackName": "",
      "spotifyUri": ""
    },
    {
      "radioStation": "M1",
      "time": "14:29",
      "pageDate": "balandžio 7d.",
      "title": "Where Is My Husband!",
      "artist": "RAYE",
      "playCount": 1,
      "spotifyArtistName": "",
      "spotifyTrackName": "",
      "spotifyUri": ""
    },
    {
      "radioStation": "M1",
      "time": "14:21",
      "pageDate": "balandžio 7d.",
      "title": "Fever Dream",
      "artist": "ALEX WARREN",
      "playCount": 1,
      "spotifyArtistName": "",
      "spotifyTrackName": "",
      "spotifyUri": ""
    },
    {
      "radioStation": "M1",
      "time": "14:14",
      "pageDate": "balandžio 7d.",
      "title": "Meiles Masina",
      "artist": "SOLO ANSAMBLIS",
      "playCount": 1,
      "spotifyArtistName": "",
      "spotifyTrackName": "",
      "spotifyUri": ""
    },
    {
      "radioStation": "M1",
      "time": "14:06",
      "pageDate": "balandžio 7d.",
      "title": "Revolution",
      "artist": "ALLE FARBEN",
      "playCount": 1,
      "spotifyArtistName": "",
      "spotifyTrackName": "",
      "spotifyUri": ""
    },
    {
      "radioStation": "M1",
      "time": "14:04",
      "pageDate": "balandžio 7d.",
      "title": "Fall At Your Feet",
      "artist": "CYRIL with DEAN LEWIS",
      "playCount": 1,
      "spotifyArtistName": "",
      "spotifyTrackName": "",
      "spotifyUri": ""
    },
    {
      "radioStation": "M1",
      "time": "13:55",
      "pageDate": "balandžio 7d.",
      "title": "Born Again",
      "artist": "LISA feat. DOJA CAT & RAYE",
      "playCount": 1,
      "spotifyArtistName": "",
      "spotifyTrackName": "",
      "spotifyUri": ""
    },
    {
      "radioStation": "M1",
      "time": "13:50",
      "pageDate": "balandžio 7d.",
      "title": "Asarom Lasa",
      "artist": "NOMBEKO AUGUSTE",
      "playCount": 1,
      "spotifyArtistName": "",
      "spotifyTrackName": "",
      "spotifyUri": ""
    },
    {
      "radioStation": "M1",
      "time": "13:42",
      "pageDate": "balandžio 7d.",
      "title": "Manchild",
      "artist": "SABRINA CARPENTER",
      "playCount": 1,
      "spotifyArtistName": "",
      "spotifyTrackName": "",
      "spotifyUri": ""
    },
    {
      "radioStation": "M1",
      "time": "13:36",
      "pageDate": "balandžio 7d.",
      "title": "Lose My Mind",
      "artist": "DON TOLIVER feat. DOJA CAT",
      "playCount": 1,
      "spotifyArtistName": "",
      "spotifyTrackName": "",
      "spotifyUri": ""
    },
    {
      "radioStation": "M1",
      "time": "13:29",
      "pageDate": "balandžio 7d.",
      "title": "Science",
      "artist": "DEADMAU5 feat. STEVIE APPLETON",
      "playCount": 1,
      "spotifyArtistName": "",
      "spotifyTrackName": "",
      "spotifyUri": ""
    },
    {
      "radioStation": "M1",
      "time": "13:26",
      "pageDate": "balandžio 7d.",
      "title": "Senorita",
      "artist": "SHAWN MENDES feat. CAMILA CABELLO",
      "playCount": 1,
      "spotifyArtistName": "",
      "spotifyTrackName": "",
      "spotifyUri": ""
    },
    {
      "radioStation": "M1",
      "time": "13:22",
      "pageDate": "balandžio 7d.",
      "title": "Rain",
      "artist": "MIKA",
      "playCount": 1,
      "spotifyArtistName": "",
      "spotifyTrackName": "",
      "spotifyUri": ""
    },
    {
      "radioStation": "M1",
      "time": "13:19",
      "pageDate": "balandžio 7d.",
      "title": "Bad Memories",
      "artist": "MEDUZA x JAMES CARTER feat. ELLEY DUHE & FAST BOY",
      "playCount": 1,
      "spotifyArtistName": "",
      "spotifyTrackName": "",
      "spotifyUri": ""
    },
    {
      "radioStation": "M1",
      "time": "13:16",
      "pageDate": "balandžio 7d.",
      "title": "Just The Way You Are",
      "artist": "MILKY x MALL GRAB",
      "playCount": 1,
      "spotifyArtistName": "",
      "spotifyTrackName": "",
      "spotifyUri": ""
    },
    {
      "radioStation": "M1",
      "time": "13:10",
      "pageDate": "balandžio 7d.",
      "title": "Pamirsk mane",
      "artist": "PAULINA PAUKSTAITYTE",
      "playCount": 1,
      "spotifyArtistName": "",
      "spotifyTrackName": "",
      "spotifyUri": ""
    },
    {
      "radioStation": "M1",
      "time": "13:03",
      "pageDate": "balandžio 7d.",
      "title": "Edge Of Desire",
      "artist": "JONAS BLUE & MALIVE",
      "playCount": 1,
      "spotifyArtistName": "",
      "spotifyTrackName": "",
      "spotifyUri": ""
    },
    {
      "radioStation": "M1",
      "time": "13:00",
      "pageDate": "balandžio 7d.",
      "title": "False Alarm",
      "artist": "MATOMA & BECKY HILL",
      "playCount": 1,
      "spotifyArtistName": "",
      "spotifyTrackName": "",
      "spotifyUri": ""
    },
    {
      "radioStation": "M1",
      "time": "12:57",
      "pageDate": "balandžio 7d.",
      "title": "Homewrecker",
      "artist": "SOMBR",
      "playCount": 1,
      "spotifyArtistName": "",
      "spotifyTrackName": "",
      "spotifyUri": ""
    },
    {
      "radioStation": "M1",
      "time": "12:54",
      "pageDate": "balandžio 7d.",
      "title": "Full Attention",
      "artist": "TOM GRENNAN",
      "playCount": 1,
      "spotifyArtistName": "",
      "spotifyTrackName": "",
      "spotifyUri": ""
    },
    {
      "radioStation": "M1",
      "time": "12:52",
      "pageDate": "balandžio 7d.",
      "title": "Make It Right",
      "artist": "TOM GREGORY x VIZE",
      "playCount": 1,
      "spotifyArtistName": "",
      "spotifyTrackName": "",
      "spotifyUri": ""
    },
    {
      "radioStation": "M1",
      "time": "12:43",
      "pageDate": "balandžio 7d.",
      "title": "Jis",
      "artist": "JOVANI, LEDI AIS",
      "playCount": 1,
      "spotifyArtistName": "",
      "spotifyTrackName": "",
      "spotifyUri": ""
    },
    {
      "radioStation": "M1",
      "time": "12:43",
      "pageDate": "balandžio 7d.",
      "title": "Abracadabra",
      "artist": "LADY GAGA",
      "playCount": 1,
      "spotifyArtistName": "",
      "spotifyTrackName": "",
      "spotifyUri": ""
    },
    {
      "radioStation": "M1",
      "time": "12:40",
      "pageDate": "balandžio 7d.",
      "title": "Younger You",
      "artist": "MILEY CYRUS",
      "playCount": 1,
      "spotifyArtistName": "",
      "spotifyTrackName": "",
      "spotifyUri": ""
    },
    {
      "radioStation": "M1",
      "time": "12:36",
      "pageDate": "balandžio 7d.",
      "title": "MONTERO (Call Me By Your Name)",
      "artist": "LIL NAS X",
      "playCount": 1,
      "spotifyArtistName": "",
      "spotifyTrackName": "",
      "spotifyUri": ""
    },
    {
      "radioStation": "M1",
      "time": "12:32",
      "pageDate": "balandžio 7d.",
      "title": "Can't Get Enough",
      "artist": "VICTORIA NADINE & KYGO",
      "playCount": 1,
      "spotifyArtistName": "",
      "spotifyTrackName": "",
      "spotifyUri": ""
    },
    {
      "radioStation": "M1",
      "time": "12:25",
      "pageDate": "balandžio 7d.",
      "title": "Dive Into The Ocean",
      "artist": "ALOK, ZEEBA, PORTUGAL. THE MAN",
      "playCount": 1,
      "spotifyArtistName": "",
      "spotifyTrackName": "",
      "spotifyUri": ""
    },
    {
      "radioStation": "M1",
      "time": "12:20",
      "pageDate": "balandžio 7d.",
      "title": "Baiana",
      "artist": "BAKERMAT",
      "playCount": 1,
      "spotifyArtistName": "",
      "spotifyTrackName": "",
      "spotifyUri": ""
    },
    {
      "radioStation": "M1",
      "time": "12:15",
      "pageDate": "balandžio 7d.",
      "title": "Sorry",
      "artist": "JUSTIN BIEBER feat. SKRILLEX & BLOOD",
      "playCount": 1,
      "spotifyArtistName": "",
      "spotifyTrackName": "",
      "spotifyUri": ""
    },
    {
      "radioStation": "M1",
      "time": "12:11",
      "pageDate": "balandžio 7d.",
      "title": "Patalai (TA'OMA remix)",
      "artist": "GABRIELE VILKICKYTE",
      "playCount": 1,
      "spotifyArtistName": "",
      "spotifyTrackName": "",
      "spotifyUri": ""
    },
    {
      "radioStation": "M1",
      "time": "12:04",
      "pageDate": "balandžio 7d.",
      "title": "Too Cool To Be Careless",
      "artist": "PAWSA",
      "playCount": 1,
      "spotifyArtistName": "",
      "spotifyTrackName": "",
      "spotifyUri": ""
    },
    {
      "radioStation": "M1",
      "time": "11:58",
      "pageDate": "balandžio 7d.",
      "title": "Shined On Me",
      "artist": "ESSEL & PAUL RICHARD",
      "playCount": 1,
      "spotifyArtistName": "",
      "spotifyTrackName": "",
      "spotifyUri": ""
    },
    {
      "radioStation": "M1",
      "time": "11:55",
      "pageDate": "balandžio 7d.",
      "title": "Mad World",
      "artist": "TWOCOLORS",
      "playCount": 1,
      "spotifyArtistName": "",
      "spotifyTrackName": "",
      "spotifyUri": ""
    },
    {
      "radioStation": "M1",
      "time": "11:49",
      "pageDate": "balandžio 7d.",
      "title": "Praeiviai",
      "artist": "ROKAS YAN",
      "playCount": 1,
      "spotifyArtistName": "",
      "spotifyTrackName": "",
      "spotifyUri": ""
    },
    {
      "radioStation": "M1",
      "time": "11:44",
      "pageDate": "balandžio 7d.",
      "title": "Heat",
      "artist": "TOVE LO & SG LEWIS",
      "playCount": 1,
      "spotifyArtistName": "",
      "spotifyTrackName": "",
      "spotifyUri": ""
    },
    {
      "radioStation": "M1",
      "time": "11:37",
      "pageDate": "balandžio 7d.",
      "title": "Beautiful",
      "artist": "ANYMA, JOJI",
      "playCount": 1,
      "spotifyArtistName": "",
      "spotifyTrackName": "",
      "spotifyUri": ""
    },
    {
      "radioStation": "M1",
      "time": "11:34",
      "pageDate": "balandžio 7d.",
      "title": "Beautiful Colors",
      "artist": "ONEREPUBLIC",
      "playCount": 1,
      "spotifyArtistName": "",
      "spotifyTrackName": "",
      "spotifyUri": ""
    },
    {
      "radioStation": "M1",
      "time": "11:29",
      "pageDate": "balandžio 7d.",
      "title": "Save My Love",
      "artist": "KYGO, KHALID, GRYFFIN",
      "playCount": 1,
      "spotifyArtistName": "",
      "spotifyTrackName": "",
      "spotifyUri": ""
    },
    {
      "radioStation": "M1",
      "time": "11:26",
      "pageDate": "balandžio 7d.",
      "title": "New Religion",
      "artist": "BEBE REXHA & FAITHLESS",
      "playCount": 1,
      "spotifyArtistName": "",
      "spotifyTrackName": "",
      "spotifyUri": ""
    },
    {
      "radioStation": "M1",
      "time": "11:24",
      "pageDate": "balandžio 7d.",
      "title": "My Loving",
      "artist": "SONNY FODERA & CHRYSTAL",
      "playCount": 1,
      "spotifyArtistName": "",
      "spotifyTrackName": "",
      "spotifyUri": ""
    },
    {
      "radioStation": "M1",
      "time": "11:19",
      "pageDate": "balandžio 7d.",
      "title": "Only Way Is Up",
      "artist": "ROBIN SCHULZ feat. IZZY BIZU",
      "playCount": 1,
      "spotifyArtistName": "",
      "spotifyTrackName": "",
      "spotifyUri": ""
    },
    {
      "radioStation": "M1",
      "time": "11:11",
      "pageDate": "balandžio 7d.",
      "title": "Italo Boogie Man",
      "artist": "BABERT",
      "playCount": 1,
      "spotifyArtistName": "",
      "spotifyTrackName": "",
      "spotifyUri": ""
    },
    {
      "radioStation": "M1",
      "time": "11:09",
      "pageDate": "balandžio 7d.",
      "title": "Lyja",
      "artist": "MANTAS BEN",
      "playCount": 1,
      "spotifyArtistName": "",
      "spotifyTrackName": "",
      "spotifyUri": ""
    },
    {
      "radioStation": "M1",
      "time": "11:03",
      "pageDate": "balandžio 7d.",
      "title": "Ego",
      "artist": "BBYCLOSE",
      "playCount": 1,
      "spotifyArtistName": "",
      "spotifyTrackName": "",
      "spotifyUri": ""
    },
    {
      "radioStation": "M1",
      "time": "11:00",
      "pageDate": "balandžio 7d.",
      "title": "Karma",
      "artist": "THE KOLORS",
      "playCount": 1,
      "spotifyArtistName": "",
      "spotifyTrackName": "",
      "spotifyUri": ""
    },
    {
      "radioStation": "M1",
      "time": "10:56",
      "pageDate": "balandžio 7d.",
      "title": "Tom's Diner",
      "artist": "SUZANNE VEGA, DNA",
      "playCount": 1,
      "spotifyArtistName": "",
      "spotifyTrackName": "",
      "spotifyUri": ""
    },
    {
      "radioStation": "M1",
      "time": "10:52",
      "pageDate": "balandžio 7d.",
      "title": "Zombie Lady",
      "artist": "DAMIANO DAVID",
      "playCount": 1,
      "spotifyArtistName": "",
      "spotifyTrackName": "",
      "spotifyUri": ""
    },
    {
      "radioStation": "M1",
      "time": "10:46",
      "pageDate": "balandžio 7d.",
      "title": "Dėl Tavęs",
      "artist": "JESSICA SHY",
      "playCount": 1,
      "spotifyArtistName": "",
      "spotifyTrackName": "",
      "spotifyUri": ""
    },
    {
      "radioStation": "M1",
      "time": "10:41",
      "pageDate": "balandžio 7d.",
      "title": "Walkman",
      "artist": "JUBEL",
      "playCount": 1,
      "spotifyArtistName": "",
      "spotifyTrackName": "",
      "spotifyUri": ""
    },
    {
      "radioStation": "M1",
      "time": "10:36",
      "pageDate": "balandžio 7d.",
      "title": "Nepamirsiu (remix)",
      "artist": "OG VERSION",
      "playCount": 1,
      "spotifyArtistName": "",
      "spotifyTrackName": "",
      "spotifyUri": ""
    },
    {
      "radioStation": "M1",
      "time": "10:33",
      "pageDate": "balandžio 7d.",
      "title": "Ghosts",
      "artist": "MOSIMANN & SKIP THE USE",
      "playCount": 1,
      "spotifyArtistName": "",
      "spotifyTrackName": "",
      "spotifyUri": ""
    },
    {
      "radioStation": "M1",
      "time": "10:30",
      "pageDate": "balandžio 7d.",
      "title": "Voyage Voyage",
      "artist": "NOVEMBER KID",
      "playCount": 1,
      "spotifyArtistName": "",
      "spotifyTrackName": "",
      "spotifyUri": ""
    },
    {
      "radioStation": "M1",
      "time": "10:26",
      "pageDate": "balandžio 7d.",
      "title": "Lose Control",
      "artist": "TEDDY SWIMS",
      "playCount": 1,
      "spotifyArtistName": "",
      "spotifyTrackName": "",
      "spotifyUri": ""
    },
    {
      "radioStation": "M1",
      "time": "10:22",
      "pageDate": "balandžio 7d.",
      "title": "There She Goes",
      "artist": "CYRIL x MOONLGHT x The LA's",
      "playCount": 1,
      "spotifyArtistName": "",
      "spotifyTrackName": "",
      "spotifyUri": ""
    },
    {
      "radioStation": "M1",
      "time": "10:16",
      "pageDate": "balandžio 7d.",
      "title": "Drive Safe",
      "artist": "MYLES SMITH & NIALL HORAN",
      "playCount": 1,
      "spotifyArtistName": "",
      "spotifyTrackName": "",
      "spotifyUri": ""
    },
    {
      "radioStation": "M1",
      "time": "10:12",
      "pageDate": "balandžio 7d.",
      "title": "Kely Sustoja Laikas",
      "artist": "ADOMAS VYSNIAUSKAS",
      "playCount": 1,
      "spotifyArtistName": "",
      "spotifyTrackName": "",
      "spotifyUri": ""
    },
    {
      "radioStation": "M1",
      "time": "10:06",
      "pageDate": "balandžio 7d.",
      "title": "So Sad So Hot",
      "artist": "CHLOE QISHA",
      "playCount": 1,
      "spotifyArtistName": "",
      "spotifyTrackName": "",
      "spotifyUri": ""
    },
    {
      "radioStation": "M1",
      "time": "10:04",
      "pageDate": "balandžio 7d.",
      "title": "Zeros",
      "artist": "CASSO x JAZZY feat. HEADIE ONE",
      "playCount": 1,
      "spotifyArtistName": "",
      "spotifyTrackName": "",
      "spotifyUri": ""
    },
    {
      "radioStation": "M1",
      "time": "09:58",
      "pageDate": "balandžio 7d.",
      "title": "Mi Amor",
      "artist": "SAM FELDT, JVKE & ANITTA",
      "playCount": 1,
      "spotifyArtistName": "",
      "spotifyTrackName": "",
      "spotifyUri": ""
    },
    {
      "radioStation": "M1",
      "time": "09:56",
      "pageDate": "balandžio 7d.",
      "title": "Touch",
      "artist": "KATSEYE",
      "playCount": 1,
      "spotifyArtistName": "",
      "spotifyTrackName": "",
      "spotifyUri": ""
    },
    {
      "radioStation": "M1",
      "time": "09:51",
      "pageDate": "balandžio 7d.",
      "title": "Phoenix",
      "artist": "MARSHMELLO x PORTUGAL. THE MAN",
      "playCount": 1,
      "spotifyArtistName": "",
      "spotifyTrackName": "",
      "spotifyUri": ""
    },
    {
      "radioStation": "M1",
      "time": "09:46",
      "pageDate": "balandžio 7d.",
      "title": "As Pakeliui",
      "artist": "JUSTINAS JARUTIS su PAULINA PAUKSTAITYTE",
      "playCount": 1,
      "spotifyArtistName": "",
      "spotifyTrackName": "",
      "spotifyUri": ""
    },
    {
      "radioStation": "M1",
      "time": "09:41",
      "pageDate": "balandžio 7d.",
      "title": "Tonto",
      "artist": "J BALVIN, RYAN CASTRO, DJ SNAKE",
      "playCount": 1,
      "spotifyArtistName": "",
      "spotifyTrackName": "",
      "spotifyUri": ""
    },
    {
      "radioStation": "M1",
      "time": "09:35",
      "pageDate": "balandžio 7d.",
      "title": "Clap Your Hands",
      "artist": "MARK KNIGHT & WH0",
      "playCount": 1,
      "spotifyArtistName": "",
      "spotifyTrackName": "",
      "spotifyUri": ""
    },
    {
      "radioStation": "M1",
      "time": "09:30",
      "pageDate": "balandžio 7d.",
      "title": "Run My Way",
      "artist": "DECEMBER 10",
      "playCount": 1,
      "spotifyArtistName": "",
      "spotifyTrackName": "",
      "spotifyUri": ""
    },
    {
      "radioStation": "M1",
      "time": "09:26",
      "pageDate": "balandžio 7d.",
      "title": "Opalite",
      "artist": "TAYLOR SWIFT",
      "playCount": 1,
      "spotifyArtistName": "",
      "spotifyTrackName": "",
      "spotifyUri": ""
    },
    {
      "radioStation": "M1",
      "time": "09:21",
      "pageDate": "balandžio 7d.",
      "title": "Can't Stop The Feeling",
      "artist": "JUSTIN TIMBERLAKE",
      "playCount": 1,
      "spotifyArtistName": "",
      "spotifyTrackName": "",
      "spotifyUri": ""
    },
    {
      "radioStation": "M1",
      "time": "09:10",
      "pageDate": "balandžio 7d.",
      "title": "1",
      "artist": "M",
      "playCount": 1,
      "spotifyArtistName": "",
      "spotifyTrackName": "",
      "spotifyUri": ""
    },
    {
      "radioStation": "M1",
      "time": "09:07",
      "pageDate": "balandžio 7d.",
      "title": "Kada Sugrisi",
      "artist": "HEAVS",
      "playCount": 1,
      "spotifyArtistName": "",
      "spotifyTrackName": "",
      "spotifyUri": ""
    },
    {
      "radioStation": "M1",
      "time": "09:04",
      "pageDate": "balandžio 7d.",
      "title": "feelslikeimfallinginlove",
      "artist": "ZERB x COLDPLAY",
      "playCount": 1,
      "spotifyArtistName": "",
      "spotifyTrackName": "",
      "spotifyUri": ""
    },
    {
      "radioStation": "M1",
      "time": "08:56",
      "pageDate": "balandžio 7d.",
      "title": "When A Woman",
      "artist": "GABRIELLE",
      "playCount": 1,
      "spotifyArtistName": "",
      "spotifyTrackName": "",
      "spotifyUri": ""
    },
    {
      "radioStation": "M1",
      "time": "08:50",
      "pageDate": "balandžio 7d.",
      "title": "Galvoj",
      "artist": "SENJASA",
      "playCount": 1,
      "spotifyArtistName": "",
      "spotifyTrackName": "",
      "spotifyUri": ""
    },
    {
      "radioStation": "M1",
      "time": "08:45",
      "pageDate": "balandžio 7d.",
      "title": "La Dadi",
      "artist": "ENISA",
      "playCount": 1,
      "spotifyArtistName": "",
      "spotifyTrackName": "",
      "spotifyUri": ""
    },
    {
      "radioStation": "M1",
      "time": "08:39",
      "pageDate": "balandžio 7d.",
      "title": "I Like It",
      "artist": "ALESSO feat. NATE SMITH",
      "playCount": 1,
      "spotifyArtistName": "",
      "spotifyTrackName": "",
      "spotifyUri": ""
    },
    {
      "radioStation": "M1",
      "time": "08:31",
      "pageDate": "balandžio 7d.",
      "title": "I Went Back To Ibiza",
      "artist": "MIKE POSNER & DAVID GUETTA",
      "playCount": 1,
      "spotifyArtistName": "",
      "spotifyTrackName": "",
      "spotifyUri": ""
    },
    {
      "radioStation": "M1",
      "time": "08:27",
      "pageDate": "balandžio 7d.",
      "title": "Ritual",
      "artist": "TIESTO feat. JONAS BLUE & RITA ORA",
      "playCount": 1,
      "spotifyArtistName": "",
      "spotifyTrackName": "",
      "spotifyUri": ""
    },
    {
      "radioStation": "M1",
      "time": "08:20",
      "pageDate": "balandžio 7d.",
      "title": "5 Minutes",
      "artist": "DON DIABLO, PINK SWEATS",
      "playCount": 1,
      "spotifyArtistName": "",
      "spotifyTrackName": "",
      "spotifyUri": ""
    },
    {
      "radioStation": "M1",
      "time": "08:14",
      "pageDate": "balandžio 7d.",
      "title": "Skambinau Bažnyčiai",
      "artist": "JUSTINAS JARUTIS x ROKAS YAN",
      "playCount": 1,
      "spotifyArtistName": "",
      "spotifyTrackName": "",
      "spotifyUri": ""
    },
    {
      "radioStation": "M1",
      "time": "08:07",
      "pageDate": "balandžio 7d.",
      "title": "I Hate That It's True",
      "artist": "DEAN LEWIS",
      "playCount": 1,
      "spotifyArtistName": "",
      "spotifyTrackName": "",
      "spotifyUri": ""
    },
    {
      "radioStation": "M1",
      "time": "08:04",
      "pageDate": "balandžio 7d.",
      "title": "Just The Way You Are",
      "artist": "MILKY x PNAU",
      "playCount": 1,
      "spotifyArtistName": "",
      "spotifyTrackName": "",
      "spotifyUri": ""
    },
    {
      "radioStation": "M1",
      "time": "07:58",
      "pageDate": "balandžio 7d.",
      "title": "Broken Strings",
      "artist": "ALAN WALKER, ISABELLA MELKMAN, KATHERINE O'RYAN",
      "playCount": 1,
      "spotifyArtistName": "",
      "spotifyTrackName": "",
      "spotifyUri": ""
    },
    {
      "radioStation": "M1",
      "time": "07:56",
      "pageDate": "balandžio 7d.",
      "title": "Dame Un Grrr (Provi Remix)",
      "artist": "FANTOMEL, KATE LINN, PROVI",
      "playCount": 1,
      "spotifyArtistName": "",
      "spotifyTrackName": "",
      "spotifyUri": ""
    },
    {
      "radioStation": "M1",
      "time": "07:50",
      "pageDate": "balandžio 7d.",
      "title": "Turbut, Kad Taip Jautiesi Kai Myli",
      "artist": "VILIUS",
      "playCount": 1,
      "spotifyArtistName": "",
      "spotifyTrackName": "",
      "spotifyUri": ""
    },
    {
      "radioStation": "M1",
      "time": "07:43",
      "pageDate": "balandžio 7d.",
      "title": "We Don't Talk Anymore",
      "artist": "CHARLIE PUTH feat. SELENA GOMEZ",
      "playCount": 1,
      "spotifyArtistName": "",
      "spotifyTrackName": "",
      "spotifyUri": ""
    },
    {
      "radioStation": "M1",
      "time": "07:37",
      "pageDate": "balandžio 7d.",
      "title": "Talk To You",
      "artist": "ANOTR, 54 ULTRA",
      "playCount": 1,
      "spotifyArtistName": "",
      "spotifyTrackName": "",
      "spotifyUri": ""
    },
    {
      "radioStation": "M1",
      "time": "07:36",
      "pageDate": "balandžio 7d.",
      "title": "I'll Be There For You",
      "artist": "REMBRANDTS",
      "playCount": 1,
      "spotifyArtistName": "",
      "spotifyTrackName": "",
      "spotifyUri": ""
    },
    {
      "radioStation": "M1",
      "time": "07:32",
      "pageDate": "balandžio 7d.",
      "title": "One Day (Vandaag)",
      "artist": "BAKERMAT",
      "playCount": 1,
      "spotifyArtistName": "",
      "spotifyTrackName": "",
      "spotifyUri": ""
    },
    {
      "radioStation": "M1",
      "time": "07:26",
      "pageDate": "balandžio 7d.",
      "title": "Birds Of A Feather (COSMIC DAWN remix)",
      "artist": "BILLIE EILISH",
      "playCount": 1,
      "spotifyArtistName": "",
      "spotifyTrackName": "",
      "spotifyUri": ""
    },
    {
      "radioStation": "M1",
      "time": "07:17",
      "pageDate": "balandžio 7d.",
      "title": "New Rules",
      "artist": "DUA LIPA",
      "playCount": 1,
      "spotifyArtistName": "",
      "spotifyTrackName": "",
      "spotifyUri": ""
    },
    {
      "radioStation": "M1",
      "time": "07:10",
      "pageDate": "balandžio 7d.",
      "title": "Apsirengus Vasara (remix)",
      "artist": "ANGELOU, SILVESTER BELT",
      "playCount": 1,
      "spotifyArtistName": "",
      "spotifyTrackName": "",
      "spotifyUri": ""
    },
    {
      "radioStation": "M1",
      "time": "07:09",
      "pageDate": "balandžio 7d.",
      "title": "Vilko Akių (The SNEEKERS remix)",
      "artist": "LOKYTĖ",
      "playCount": 1,
      "spotifyArtistName": "",
      "spotifyTrackName": "",
      "spotifyUri": ""
    },
    {
      "radioStation": "M1",
      "time": "07:07",
      "pageDate": "balandžio 7d.",
      "title": "Guilty",
      "artist": "BLANKA",
      "playCount": 1,
      "spotifyArtistName": "",
      "spotifyTrackName": "",
      "spotifyUri": ""
    },
    {
      "radioStation": "M1",
      "time": "07:04",
      "pageDate": "balandžio 7d.",
      "title": "Dive Into Me",
      "artist": "ALOK, KHALID",
      "playCount": 1,
      "spotifyArtistName": "",
      "spotifyTrackName": "",
      "spotifyUri": ""
    },
    {
      "radioStation": "M1",
      "time": "06:57",
      "pageDate": "balandžio 7d.",
      "title": "Happiness",
      "artist": "ALEXIS JORDAN",
      "playCount": 1,
      "spotifyArtistName": "",
      "spotifyTrackName": "",
      "spotifyUri": ""
    },
    {
      "radioStation": "M1",
      "time": "06:54",
      "pageDate": "balandžio 7d.",
      "title": "Handlebars",
      "artist": "JENNIE feat. DUA LIPA",
      "playCount": 1,
      "spotifyArtistName": "",
      "spotifyTrackName": "",
      "spotifyUri": ""
    },
    {
      "radioStation": "M1",
      "time": "06:49",
      "pageDate": "balandžio 7d.",
      "title": "Man I Need",
      "artist": "OLIVIA DEAN",
      "playCount": 1,
      "spotifyArtistName": "",
      "spotifyTrackName": "",
      "spotifyUri": ""
    },
    {
      "radioStation": "M1",
      "time": "06:41",
      "pageDate": "balandžio 7d.",
      "title": "So Many Colours",
      "artist": "SUB FOCUS, POPPY BASKCOMB",
      "playCount": 1,
      "spotifyArtistName": "",
      "spotifyTrackName": "",
      "spotifyUri": ""
    },
    {
      "radioStation": "M1",
      "time": "06:37",
      "pageDate": "balandžio 7d.",
      "title": "Speed Demon",
      "artist": "JUSTIN BIEBER",
      "playCount": 1,
      "spotifyArtistName": "",
      "spotifyTrackName": "",
      "spotifyUri": ""
    },
    {
      "radioStation": "M1",
      "time": "06:28",
      "pageDate": "balandžio 7d.",
      "title": "Mama",
      "artist": "JONAS BLUE feat. WILLIAM SINGE",
      "playCount": 1,
      "spotifyArtistName": "",
      "spotifyTrackName": "",
      "spotifyUri": ""
    },
    {
      "radioStation": "M1",
      "time": "06:25",
      "pageDate": "balandžio 7d.",
      "title": "Tyli",
      "artist": "JOVANI x NORBERTAS x ELZY",
      "playCount": 1,
      "spotifyArtistName": "",
      "spotifyTrackName": "",
      "spotifyUri": ""
    },
    {
      "radioStation": "M1",
      "time": "06:23",
      "pageDate": "balandžio 7d.",
      "title": "Body Talk",
      "artist": "ALLE FARBEN feat. RENE MILLER",
      "playCount": 1,
      "spotifyArtistName": "",
      "spotifyTrackName": "",
      "spotifyUri": ""
    },
    {
      "radioStation": "M1",
      "time": "06:19",
      "pageDate": "balandžio 7d.",
      "title": "Uptown Funk",
      "artist": "MARK RONSON ft. BRUNO MARS",
      "playCount": 1,
      "spotifyArtistName": "",
      "spotifyTrackName": "",
      "spotifyUri": ""
    },
    {
      "radioStation": "M1",
      "time": "06:15",
      "pageDate": "balandžio 7d.",
      "title": "Up & Down (Don't Fall In Love With Me)",
      "artist": "MIND ENTERPRISES, JOE KILINGTON",
      "playCount": 1,
      "spotifyArtistName": "",
      "spotifyTrackName": "",
      "spotifyUri": ""
    },
    {
      "radioStation": "M1",
      "time": "06:12",
      "pageDate": "balandžio 7d.",
      "title": "Younger You",
      "artist": "MILEY CYRUS",
      "playCount": 1,
      "spotifyArtistName": "",
      "spotifyTrackName": "",
      "spotifyUri": ""
    },
    {
      "radioStation": "M1",
      "time": "06:09",
      "pageDate": "balandžio 7d.",
      "title": "Call On Me",
      "artist": "ERIC PRYDZ",
      "playCount": 1,
      "spotifyArtistName": "",
      "spotifyTrackName": "",
      "spotifyUri": ""
    },
    {
      "radioStation": "M1",
      "time": "06:06",
      "pageDate": "balandžio 7d.",
      "title": "Vaikai Po Lelijom",
      "artist": "BARDACIOKAS",
      "playCount": 1,
      "spotifyArtistName": "",
      "spotifyTrackName": "",
      "spotifyUri": ""
    },
    {
      "radioStation": "M1",
      "time": "06:03",
      "pageDate": "balandžio 7d.",
      "title": "Yeke Yeke",
      "artist": "NOEL HOLLER x PICCO",
      "playCount": 1,
      "spotifyArtistName": "",
      "spotifyTrackName": "",
      "spotifyUri": ""
    },
    {
      "radioStation": "M1",
      "time": "06:00",
      "pageDate": "balandžio 7d.",
      "title": "Guilty",
      "artist": "TEDDY SWIMS",
      "playCount": 1,
      "spotifyArtistName": "",
      "spotifyTrackName": "",
      "spotifyUri": ""
    },
    {
      "radioStation": "M1",
      "time": "05:58",
      "pageDate": "balandžio 7d.",
      "title": "It's A Feeling",
      "artist": "SIGALA x TREVOR DANIEL x 24KGOLDN",
      "playCount": 1,
      "spotifyArtistName": "",
      "spotifyTrackName": "",
      "spotifyUri": ""
    },
    {
      "radioStation": "M1",
      "time": "05:55",
      "pageDate": "balandžio 7d.",
      "title": "Is Tu Akiu",
      "artist": "ROKAS YAN",
      "playCount": 1,
      "spotifyArtistName": "",
      "spotifyTrackName": "",
      "spotifyUri": ""
    },
    {
      "radioStation": "M1",
      "time": "05:52",
      "pageDate": "balandžio 7d.",
      "title": "Lioness",
      "artist": "SWEDISH HOUSE MAFIA x NIKKI & THE DOVE",
      "playCount": 1,
      "spotifyArtistName": "",
      "spotifyTrackName": "",
      "spotifyUri": ""
    },
    {
      "radioStation": "M1",
      "time": "05:48",
      "pageDate": "balandžio 7d.",
      "title": "To Love Somebody",
      "artist": "HOLLY HUMBERSTONE",
      "playCount": 1,
      "spotifyArtistName": "",
      "spotifyTrackName": "",
      "spotifyUri": ""
    },
    {
      "radioStation": "M1",
      "time": "05:44",
      "pageDate": "balandžio 7d.",
      "title": "Wake Me Up",
      "artist": "AVICII",
      "playCount": 1,
      "spotifyArtistName": "",
      "spotifyTrackName": "",
      "spotifyUri": ""
    },
    {
      "radioStation": "M1",
      "time": "05:40",
      "pageDate": "balandžio 7d.",
      "title": "Blessings",
      "artist": "CALVIN HARRIS & CLEMENTINE DOUGLAS",
      "playCount": 1,
      "spotifyArtistName": "",
      "spotifyTrackName": "",
      "spotifyUri": ""
    },
    {
      "radioStation": "M1",
      "time": "05:38",
      "pageDate": "balandžio 7d.",
      "title": "Swim",
      "artist": "BTS",
      "playCount": 1,
      "spotifyArtistName": "",
      "spotifyTrackName": "",
      "spotifyUri": ""
    },
    {
      "radioStation": "M1",
      "time": "05:34",
      "pageDate": "balandžio 7d.",
      "title": "Lost",
      "artist": "VINTAGE CULTURE, GABSS",
      "playCount": 1,
      "spotifyArtistName": "",
      "spotifyTrackName": "",
      "spotifyUri": ""
    },
    {
      "radioStation": "M1",
      "time": "05:31",
      "pageDate": "balandžio 7d.",
      "title": "Layla",
      "artist": "DYNORO & ARASH",
      "playCount": 1,
      "spotifyArtistName": "",
      "spotifyTrackName": "",
      "spotifyUri": ""
    },
    {
      "radioStation": "M1",
      "time": "05:29",
      "pageDate": "balandžio 7d.",
      "title": "Guestlist",
      "artist": "CASSO feat. SACHA",
      "playCount": 1,
      "spotifyArtistName": "",
      "spotifyTrackName": "",
      "spotifyUri": ""
    },
    {
      "radioStation": "M1",
      "time": "05:27",
      "pageDate": "balandžio 7d.",
      "title": "Lauzai (SAUBEN remix)",
      "artist": "HIPERBOLE",
      "playCount": 1,
      "spotifyArtistName": "",
      "spotifyTrackName": "",
      "spotifyUri": ""
    },
    {
      "radioStation": "M1",
      "time": "05:24",
      "pageDate": "balandžio 7d.",
      "title": "Loco Loco",
      "artist": "GORDO & REINIER ZONNEVELD",
      "playCount": 1,
      "spotifyArtistName": "",
      "spotifyTrackName": "",
      "spotifyUri": ""
    },
    {
      "radioStation": "M1",
      "time": "05:21",
      "pageDate": "balandžio 7d.",
      "title": "Dream Machine",
      "artist": "PURPLE DISCO MACHINE & ALISON GOLDFRAPP",
      "playCount": 1,
      "spotifyArtistName": "",
      "spotifyTrackName": "",
      "spotifyUri": ""
    },
    {
      "radioStation": "M1",
      "time": "05:18",
      "pageDate": "balandžio 7d.",
      "title": "Cohete",
      "artist": "SHAKIRA, RAUW ALEJANDRO",
      "playCount": 1,
      "spotifyArtistName": "",
      "spotifyTrackName": "",
      "spotifyUri": ""
    },
    {
      "radioStation": "M1",
      "time": "05:14",
      "pageDate": "balandžio 7d.",
      "title": "Bad Habits",
      "artist": "ED SHEERAN",
      "playCount": 1,
      "spotifyArtistName": "",
      "spotifyTrackName": "",
      "spotifyUri": ""
    },
    {
      "radioStation": "M1",
      "time": "05:12",
      "pageDate": "balandžio 7d.",
      "title": "Sinners",
      "artist": "DEEPEND, SAM FELDT, OUTLIERS",
      "playCount": 1,
      "spotifyArtistName": "",
      "spotifyTrackName": "",
      "spotifyUri": ""
    },
    {
      "radioStation": "M1",
      "time": "05:08",
      "pageDate": "balandžio 7d.",
      "title": "Ordinary World",
      "artist": "ADAM LAMBERT",
      "playCount": 1,
      "spotifyArtistName": "",
      "spotifyTrackName": "",
      "spotifyUri": ""
    },
    {
      "radioStation": "M1",
      "time": "05:05",
      "pageDate": "balandžio 7d.",
      "title": "Myli Nemyli",
      "artist": "IGLE",
      "playCount": 1,
      "spotifyArtistName": "",
      "spotifyTrackName": "",
      "spotifyUri": ""
    },
    {
      "radioStation": "M1",
      "time": "05:03",
      "pageDate": "balandžio 7d.",
      "title": "Underneath The Blue",
      "artist": "MOSIMANN feat. JOE CEERE",
      "playCount": 1,
      "spotifyArtistName": "",
      "spotifyTrackName": "",
      "spotifyUri": ""
    },
    {
      "radioStation": "M1",
      "time": "05:00",
      "pageDate": "balandžio 7d.",
      "title": "I Found You",
      "artist": "BENNY BLANCO feat. CALVIN HARRIS",
      "playCount": 1,
      "spotifyArtistName": "",
      "spotifyTrackName": "",
      "spotifyUri": ""
    },
    {
      "radioStation": "M1",
      "time": "04:57",
      "pageDate": "balandžio 7d.",
      "title": "Drive Safe",
      "artist": "MYLES SMITH & NIALL HORAN",
      "playCount": 1,
      "spotifyArtistName": "",
      "spotifyTrackName": "",
      "spotifyUri": ""
    },
    {
      "radioStation": "M1",
      "time": "04:54",
      "pageDate": "balandžio 7d.",
      "title": "Velumoj",
      "artist": "MARTYNAS KAVALIAUSKAS",
      "playCount": 1,
      "spotifyArtistName": "",
      "spotifyTrackName": "",
      "spotifyUri": ""
    },
    {
      "radioStation": "M1",
      "time": "04:50",
      "pageDate": "balandžio 7d.",
      "title": "The Right",
      "artist": "DJ SEINFELD & CONFIDENCE MAN",
      "playCount": 1,
      "spotifyArtistName": "",
      "spotifyTrackName": "",
      "spotifyUri": ""
    },
    {
      "radioStation": "M1",
      "time": "04:47",
      "pageDate": "balandžio 7d.",
      "title": "La La La",
      "artist": "WILL ARMEX",
      "playCount": 1,
      "spotifyArtistName": "",
      "spotifyTrackName": "",
      "spotifyUri": ""
    },
    {
      "radioStation": "M1",
      "time": "04:44",
      "pageDate": "balandžio 7d.",
      "title": "Drive",
      "artist": "BLACK COFFEE feat. DAVID GUETTA & DELILAH MONTAGU",
      "playCount": 1,
      "spotifyArtistName": "",
      "spotifyTrackName": "",
      "spotifyUri": ""
    },
    {
      "radioStation": "M1",
      "time": "04:40",
      "pageDate": "balandžio 7d.",
      "title": "Anxiety",
      "artist": "DOECHII",
      "playCount": 1,
      "spotifyArtistName": "",
      "spotifyTrackName": "",
      "spotifyUri": ""
    },
    {
      "radioStation": "M1",
      "time": "04:36",
      "pageDate": "balandžio 7d.",
      "title": "Disney Princess",
      "artist": "MELANIE MARTINEZ",
      "playCount": 1,
      "spotifyArtistName": "",
      "spotifyTrackName": "",
      "spotifyUri": ""
    },
    {
      "radioStation": "M1",
      "time": "04:33",
      "pageDate": "balandžio 7d.",
      "title": "Apagame",
      "artist": "ALVARO SOLER",
      "playCount": 1,
      "spotifyArtistName": "",
      "spotifyTrackName": "",
      "spotifyUri": ""
    },
    {
      "radioStation": "M1",
      "time": "04:30",
      "pageDate": "balandžio 7d.",
      "title": "Skambinau Bažnyčiai",
      "artist": "JUSTINAS JARUTIS x ROKAS YAN",
      "playCount": 1,
      "spotifyArtistName": "",
      "spotifyTrackName": "",
      "spotifyUri": ""
    },
    {
      "radioStation": "M1",
      "time": "04:27",
      "pageDate": "balandžio 7d.",
      "title": "Forever Young",
      "artist": "DAVID GUETTA, ALPHAVILLE & AVA MAX",
      "playCount": 1,
      "spotifyArtistName": "",
      "spotifyTrackName": "",
      "spotifyUri": ""
    },
    {
      "radioStation": "M1",
      "time": "04:24",
      "pageDate": "balandžio 7d.",
      "title": "Save Me Tonight",
      "artist": "JENNIFER LOPEZ x DAVID GUETTA",
      "playCount": 1,
      "spotifyArtistName": "",
      "spotifyTrackName": "",
      "spotifyUri": ""
    },
    {
      "radioStation": "M1",
      "time": "04:21",
      "pageDate": "balandžio 7d.",
      "title": "Show Me Love",
      "artist": "SAM FELDT",
      "playCount": 1,
      "spotifyArtistName": "",
      "spotifyTrackName": "",
      "spotifyUri": ""
    },
    {
      "radioStation": "M1",
      "time": "04:17",
      "pageDate": "balandžio 7d.",
      "title": "I Wanna Dance With Somebody (Who Loves Me)",
      "artist": "CALUM SCOTT x WHITNEY HOUSTON",
      "playCount": 1,
      "spotifyArtistName": "",
      "spotifyTrackName": "",
      "spotifyUri": ""
    },
    {
      "radioStation": "M1",
      "time": "04:15",
      "pageDate": "balandžio 7d.",
      "title": "Disco Cone (Take It High)",
      "artist": "ENISA feat. WENZL MCGOWEN",
      "playCount": 1,
      "spotifyArtistName": "",
      "spotifyTrackName": "",
      "spotifyUri": ""
    },
    {
      "radioStation": "M1",
      "time": "04:11",
      "pageDate": "balandžio 7d.",
      "title": "Get Away",
      "artist": "KUNGS feat. BOYS NOIZE",
      "playCount": 1,
      "spotifyArtistName": "",
      "spotifyTrackName": "",
      "spotifyUri": ""
    },
    {
      "radioStation": "M1",
      "time": "04:08",
      "pageDate": "balandžio 7d.",
      "title": "Lean On",
      "artist": "MAJOR LAZER x DJ SNAKE feat. MO",
      "playCount": 1,
      "spotifyArtistName": "",
      "spotifyTrackName": "",
      "spotifyUri": ""
    },
    {
      "radioStation": "M1",
      "time": "04:05",
      "pageDate": "balandžio 7d.",
      "title": "Nieko Nera",
      "artist": "SISTERS ON WIRE",
      "playCount": 1,
      "spotifyArtistName": "",
      "spotifyTrackName": "",
      "spotifyUri": ""
    },
    {
      "radioStation": "M1",
      "time": "04:03",
      "pageDate": "balandžio 7d.",
      "title": "Bus Station",
      "artist": "MINELLI",
      "playCount": 1,
      "spotifyArtistName": "",
      "spotifyTrackName": "",
      "spotifyUri": ""
    },
    {
      "radioStation": "M1",
      "time": "04:00",
      "pageDate": "balandžio 7d.",
      "title": "You",
      "artist": "BUNT & OAKS",
      "playCount": 1,
      "spotifyArtistName": "",
      "spotifyTrackName": "",
      "spotifyUri": ""
    },
    {
      "radioStation": "M1",
      "time": "03:56",
      "pageDate": "balandžio 7d.",
      "title": "Unwritten",
      "artist": "NATASHA BEDINGFIELD",
      "playCount": 1,
      "spotifyArtistName": "",
      "spotifyTrackName": "",
      "spotifyUri": ""
    },
    {
      "radioStation": "M1",
      "time": "03:51",
      "pageDate": "balandžio 7d.",
      "title": "Kitoks Pasaulis 2017",
      "artist": "ANDRIUS MAMONTOVAS",
      "playCount": 1,
      "spotifyArtistName": "",
      "spotifyTrackName": "",
      "spotifyUri": ""
    },
    {
      "radioStation": "M1",
      "time": "03:49",
      "pageDate": "balandžio 7d.",
      "title": "BANG BANG",
      "artist": "FELIX JAEHN x LEONY",
      "playCount": 1,
      "spotifyArtistName": "",
      "spotifyTrackName": "",
      "spotifyUri": ""
    },
    {
      "radioStation": "M1",
      "time": "03:46",
      "pageDate": "balandžio 7d.",
      "title": "Just The Way You Are",
      "artist": "MILKY x MALL GRAB",
      "playCount": 1,
      "spotifyArtistName": "",
      "spotifyTrackName": "",
      "spotifyUri": ""
    },
    {
      "radioStation": "M1",
      "time": "03:42",
      "pageDate": "balandžio 7d.",
      "title": "Rude",
      "artist": "MAGIC!",
      "playCount": 1,
      "spotifyArtistName": "",
      "spotifyTrackName": "",
      "spotifyUri": ""
    },
    {
      "radioStation": "M1",
      "time": "03:39",
      "pageDate": "balandžio 7d.",
      "title": "Is That For Me",
      "artist": "ALESSO feat. ANITTA",
      "playCount": 1,
      "spotifyArtistName": "",
      "spotifyTrackName": "",
      "spotifyUri": ""
    },
    {
      "radioStation": "M1",
      "time": "03:37",
      "pageDate": "balandžio 7d.",
      "title": "Tears",
      "artist": "SABRINA CARPENTER",
      "playCount": 1,
      "spotifyArtistName": "",
      "spotifyTrackName": "",
      "spotifyUri": ""
    },
    {
      "radioStation": "M1",
      "time": "03:33",
      "pageDate": "balandžio 7d.",
      "title": "Homewrecker",
      "artist": "SOMBR",
      "playCount": 1,
      "spotifyArtistName": "",
      "spotifyTrackName": "",
      "spotifyUri": ""
    },
    {
      "radioStation": "M1",
      "time": "03:31",
      "pageDate": "balandžio 7d.",
      "title": "Visa Save",
      "artist": "LIEPA",
      "playCount": 1,
      "spotifyArtistName": "",
      "spotifyTrackName": "",
      "spotifyUri": ""
    },
    {
      "radioStation": "M1",
      "time": "03:28",
      "pageDate": "balandžio 7d.",
      "title": "New Religion",
      "artist": "BEBE REXHA & FAITHLESS",
      "playCount": 1,
      "spotifyArtistName": "",
      "spotifyTrackName": "",
      "spotifyUri": ""
    },
    {
      "radioStation": "M1",
      "time": "03:25",
      "pageDate": "balandžio 7d.",
      "title": "Frequency",
      "artist": "WATERMAT & TAI",
      "playCount": 1,
      "spotifyArtistName": "",
      "spotifyTrackName": "",
      "spotifyUri": ""
    },
    {
      "radioStation": "M1",
      "time": "03:22",
      "pageDate": "balandžio 7d.",
      "title": "Messy",
      "artist": "LOLA YOUNG",
      "playCount": 1,
      "spotifyArtistName": "",
      "spotifyTrackName": "",
      "spotifyUri": ""
    },
    {
      "radioStation": "M1",
      "time": "03:18",
      "pageDate": "balandžio 7d.",
      "title": "Love Me Like You Do",
      "artist": "ELLIE GOULDING",
      "playCount": 1,
      "spotifyArtistName": "",
      "spotifyTrackName": "",
      "spotifyUri": ""
    },
    {
      "radioStation": "M1",
      "time": "03:15",
      "pageDate": "balandžio 7d.",
      "title": "Turn The Lights Off",
      "artist": "KATO feat. JON",
      "playCount": 1,
      "spotifyArtistName": "",
      "spotifyTrackName": "",
      "spotifyUri": ""
    },
    {
      "radioStation": "M1",
      "time": "03:12",
      "pageDate": "balandžio 7d.",
      "title": "Nebegaliu Sokt Be Taves",
      "artist": "MANTAS BEN",
      "playCount": 1,
      "spotifyArtistName": "",
      "spotifyTrackName": "",
      "spotifyUri": ""
    },
    {
      "radioStation": "M1",
      "time": "03:08",
      "pageDate": "balandžio 7d.",
      "title": "Houdini",
      "artist": "EMINEM",
      "playCount": 1,
      "spotifyArtistName": "",
      "spotifyTrackName": "",
      "spotifyUri": ""
    },
    {
      "radioStation": "M1",
      "time": "03:04",
      "pageDate": "balandžio 7d.",
      "title": "Birds Of A Feather (COSMIC DAWN remix)",
      "artist": "BILLIE EILISH",
      "playCount": 1,
      "spotifyArtistName": "",
      "spotifyTrackName": "",
      "spotifyUri": ""
    },
    {
      "radioStation": "M1",
      "time": "03:00",
      "pageDate": "balandžio 7d.",
      "title": "One Foot",
      "artist": "WALK THE MOON",
      "playCount": 1,
      "spotifyArtistName": "",
      "spotifyTrackName": "",
      "spotifyUri": ""
    },
    {
      "radioStation": "M1",
      "time": "02:58",
      "pageDate": "balandžio 7d.",
      "title": "Just The Way You Are",
      "artist": "BRUNO MARS",
      "playCount": 1,
      "spotifyArtistName": "",
      "spotifyTrackName": "",
      "spotifyUri": ""
    },
    {
      "radioStation": "M1",
      "time": "02:54",
      "pageDate": "balandžio 7d.",
      "title": "Catharina",
      "artist": "MARTIN GARRIX",
      "playCount": 1,
      "spotifyArtistName": "",
      "spotifyTrackName": "",
      "spotifyUri": ""
    },
    {
      "radioStation": "M1",
      "time": "02:51",
      "pageDate": "balandžio 7d.",
      "title": "Dusia",
      "artist": "LEON SOMOV & MONIKA LINKYTE",
      "playCount": 1,
      "spotifyArtistName": "",
      "spotifyTrackName": "",
      "spotifyUri": ""
    },
    {
      "radioStation": "M1",
      "time": "02:48",
      "pageDate": "balandžio 7d.",
      "title": "Only You",
      "artist": "SHOUSE & CUB SPORT",
      "playCount": 1,
      "spotifyArtistName": "",
      "spotifyTrackName": "",
      "spotifyUri": ""
    },
    {
      "radioStation": "M1",
      "time": "02:46",
      "pageDate": "balandžio 7d.",
      "title": "Fever Dream",
      "artist": "ALEX WARREN",
      "playCount": 1,
      "spotifyArtistName": "",
      "spotifyTrackName": "",
      "spotifyUri": ""
    },
    {
      "radioStation": "M1",
      "time": "02:42",
      "pageDate": "balandžio 7d.",
      "title": "Holy Father",
      "artist": "KLANGKARUSSELL, OLIVA",
      "playCount": 1,
      "spotifyArtistName": "",
      "spotifyTrackName": "",
      "spotifyUri": ""
    },
    {
      "radioStation": "M1",
      "time": "02:39",
      "pageDate": "balandžio 7d.",
      "title": "What You Want",
      "artist": "ANGELE feat. JUSTICE",
      "playCount": 1,
      "spotifyArtistName": "",
      "spotifyTrackName": "",
      "spotifyUri": ""
    },
    {
      "radioStation": "M1",
      "time": "02:37",
      "pageDate": "balandžio 7d.",
      "title": "Sunroof",
      "artist": "NICKY YOURE feat. DAZY",
      "playCount": 1,
      "spotifyArtistName": "",
      "spotifyTrackName": "",
      "spotifyUri": ""
    },
    {
      "radioStation": "M1",
      "time": "02:34",
      "pageDate": "balandžio 7d.",
      "title": "No Broke Boys",
      "artist": "DISCO LINES & TINASHE",
      "playCount": 1,
      "spotifyArtistName": "",
      "spotifyTrackName": "",
      "spotifyUri": ""
    },
    {
      "radioStation": "M1",
      "time": "02:31",
      "pageDate": "balandžio 7d.",
      "title": "Naktyje",
      "artist": "JAZZU",
      "playCount": 1,
      "spotifyArtistName": "",
      "spotifyTrackName": "",
      "spotifyUri": ""
    },
    {
      "radioStation": "M1",
      "time": "02:28",
      "pageDate": "balandžio 7d.",
      "title": "I Went Back To Ibiza",
      "artist": "MIKE POSNER & DAVID GUETTA",
      "playCount": 1,
      "spotifyArtistName": "",
      "spotifyTrackName": "",
      "spotifyUri": ""
    },
    {
      "radioStation": "M1",
      "time": "02:25",
      "pageDate": "balandžio 7d.",
      "title": "Mountains",
      "artist": "JONAS BLUE, GALANTIS, ZOE WEES",
      "playCount": 1,
      "spotifyArtistName": "",
      "spotifyTrackName": "",
      "spotifyUri": ""
    },
    {
      "radioStation": "M1",
      "time": "02:23",
      "pageDate": "balandžio 7d.",
      "title": "Mantra",
      "artist": "JENNIE",
      "playCount": 1,
      "spotifyArtistName": "",
      "spotifyTrackName": "",
      "spotifyUri": ""
    },
    {
      "radioStation": "M1",
      "time": "02:20",
      "pageDate": "balandžio 7d.",
      "title": "Hold On",
      "artist": "NATHAN DAWE & ABI FLYNN",
      "playCount": 1,
      "spotifyArtistName": "",
      "spotifyTrackName": "",
      "spotifyUri": ""
    },
    {
      "radioStation": "M1",
      "time": "02:17",
      "pageDate": "balandžio 7d.",
      "title": "Unsure",
      "artist": "ALAN WALKER & KYLIE CANTRALL",
      "playCount": 1,
      "spotifyArtistName": "",
      "spotifyTrackName": "",
      "spotifyUri": ""
    },
    {
      "radioStation": "M1",
      "time": "02:14",
      "pageDate": "balandžio 7d.",
      "title": "American Girls",
      "artist": "HARRY STYLES",
      "playCount": 1,
      "spotifyArtistName": "",
      "spotifyTrackName": "",
      "spotifyUri": ""
    },
    {
      "radioStation": "M1",
      "time": "02:10",
      "pageDate": "balandžio 7d.",
      "title": "Roar",
      "artist": "KATY PERRY",
      "playCount": 1,
      "spotifyArtistName": "",
      "spotifyTrackName": "",
      "spotifyUri": ""
    },
    {
      "radioStation": "M1",
      "time": "02:07",
      "pageDate": "balandžio 7d.",
      "title": "Miegok Ramiai",
      "artist": "GJAN",
      "playCount": 1,
      "spotifyArtistName": "",
      "spotifyTrackName": "",
      "spotifyUri": ""
    },
    {
      "radioStation": "M1",
      "time": "02:04",
      "pageDate": "balandžio 7d.",
      "title": "Kite",
      "artist": "BENJAMIN INGROSSO with OLLY ALEXANDER",
      "playCount": 1,
      "spotifyArtistName": "",
      "spotifyTrackName": "",
      "spotifyUri": ""
    },
    {
      "radioStation": "M1",
      "time": "02:00",
      "pageDate": "balandžio 7d.",
      "title": "Pasaporte",
      "artist": "RAUW ALEJANDRO, Mr. NAISGAI",
      "playCount": 1,
      "spotifyArtistName": "",
      "spotifyTrackName": "",
      "spotifyUri": ""
    },
    {
      "radioStation": "M1",
      "time": "01:57",
      "pageDate": "balandžio 7d.",
      "title": "Beautiful Colors",
      "artist": "ONEREPUBLIC",
      "playCount": 1,
      "spotifyArtistName": "",
      "spotifyTrackName": "",
      "spotifyUri": ""
    },
    {
      "radioStation": "M1",
      "time": "01:54",
      "pageDate": "balandžio 7d.",
      "title": "Tas Jausmas",
      "artist": "SAULIUS PRUSAITIS ir IGLE",
      "playCount": 1,
      "spotifyArtistName": "",
      "spotifyTrackName": "",
      "spotifyUri": ""
    },
    {
      "radioStation": "M1",
      "time": "01:51",
      "pageDate": "balandžio 7d.",
      "title": "Say No Prayer",
      "artist": "OSKAR MED K x IZZY BIZU",
      "playCount": 1,
      "spotifyArtistName": "",
      "spotifyTrackName": "",
      "spotifyUri": ""
    },
    {
      "radioStation": "M1",
      "time": "01:49",
      "pageDate": "balandžio 7d.",
      "title": "Somebody (2024)",
      "artist": "GOTYE, FISHER, CHRIS LAKE, KIMBRA, SANTE SANSONE",
      "playCount": 1,
      "spotifyArtistName": "",
      "spotifyTrackName": "",
      "spotifyUri": ""
    },
    {
      "radioStation": "M1",
      "time": "01:46",
      "pageDate": "balandžio 7d.",
      "title": "Sweet Caroline (TWO FRIENDS remix)",
      "artist": "NEIL DIAMOND",
      "playCount": 1,
      "spotifyArtistName": "",
      "spotifyTrackName": "",
      "spotifyUri": ""
    },
    {
      "radioStation": "M1",
      "time": "01:42",
      "pageDate": "balandžio 7d.",
      "title": "Diamonds",
      "artist": "RIHANNA",
      "playCount": 1,
      "spotifyArtistName": "",
      "spotifyTrackName": "",
      "spotifyUri": ""
    },
    {
      "radioStation": "M1",
      "time": "01:40",
      "pageDate": "balandžio 7d.",
      "title": "Voyage Voyage",
      "artist": "NOVEMBER KID",
      "playCount": 1,
      "spotifyArtistName": "",
      "spotifyTrackName": "",
      "spotifyUri": ""
    },
    {
      "radioStation": "M1",
      "time": "01:36",
      "pageDate": "balandžio 7d.",
      "title": "Hold My Hand",
      "artist": "JESS GLYNNE",
      "playCount": 1,
      "spotifyArtistName": "",
      "spotifyTrackName": "",
      "spotifyUri": ""
    },
    {
      "radioStation": "M1",
      "time": "01:33",
      "pageDate": "balandžio 7d.",
      "title": "Eyes Closed",
      "artist": "IMAGINE DRAGONS",
      "playCount": 1,
      "spotifyArtistName": "",
      "spotifyTrackName": "",
      "spotifyUri": ""
    },
    {
      "radioStation": "M1",
      "time": "01:30",
      "pageDate": "balandžio 7d.",
      "title": "Nebeliko Nieko",
      "artist": "ROKAS YAN",
      "playCount": 1,
      "spotifyArtistName": "",
      "spotifyTrackName": "",
      "spotifyUri": ""
    },
    {
      "radioStation": "M1",
      "time": "01:28",
      "pageDate": "balandžio 7d.",
      "title": "Cheri Cheri Lady",
      "artist": "MALENA",
      "playCount": 1,
      "spotifyArtistName": "",
      "spotifyTrackName": "",
      "spotifyUri": ""
    },
    {
      "radioStation": "M1",
      "time": "01:25",
      "pageDate": "balandžio 7d.",
      "title": "Dive Into Me",
      "artist": "ALOK, KHALID",
      "playCount": 1,
      "spotifyArtistName": "",
      "spotifyTrackName": "",
      "spotifyUri": ""
    },
    {
      "radioStation": "M1",
      "time": "01:22",
      "pageDate": "balandžio 7d.",
      "title": "Fria",
      "artist": "ENRIQUE IGLESIAS x YOTUEL",
      "playCount": 1,
      "spotifyArtistName": "",
      "spotifyTrackName": "",
      "spotifyUri": ""
    },
    {
      "radioStation": "M1",
      "time": "01:19",
      "pageDate": "balandžio 7d.",
      "title": "Hush Baby, Hurry Slowly",
      "artist": "SIGRID",
      "playCount": 1,
      "spotifyArtistName": "",
      "spotifyTrackName": "",
      "spotifyUri": ""
    },
    {
      "radioStation": "M1",
      "time": "01:17",
      "pageDate": "balandžio 7d.",
      "title": "Only You",
      "artist": "SIGMA x SACHA",
      "playCount": 1,
      "spotifyArtistName": "",
      "spotifyTrackName": "",
      "spotifyUri": ""
    },
    {
      "radioStation": "M1",
      "time": "01:14",
      "pageDate": "balandžio 7d.",
      "title": "Levels",
      "artist": "AVICII",
      "playCount": 1,
      "spotifyArtistName": "",
      "spotifyTrackName": "",
      "spotifyUri": ""
    },
    {
      "radioStation": "M1",
      "time": "01:10",
      "pageDate": "balandžio 7d.",
      "title": "Come Find Me",
      "artist": "MK x CLEMENTINE DOUGLAS",
      "playCount": 1,
      "spotifyArtistName": "",
      "spotifyTrackName": "",
      "spotifyUri": ""
    },
    {
      "radioStation": "M1",
      "time": "01:08",
      "pageDate": "balandžio 7d.",
      "title": "Kur Tu",
      "artist": "NORBERTAS",
      "playCount": 1,
      "spotifyArtistName": "",
      "spotifyTrackName": "",
      "spotifyUri": ""
    },
    {
      "radioStation": "M1",
      "time": "01:05",
      "pageDate": "balandžio 7d.",
      "title": "Say My Name",
      "artist": "BURAK YETER x PARKAH & DURZO",
      "playCount": 1,
      "spotifyArtistName": "",
      "spotifyTrackName": "",
      "spotifyUri": ""
    },
    {
      "radioStation": "M1",
      "time": "01:03",
      "pageDate": "balandžio 7d.",
      "title": "Supernatural",
      "artist": "ARIANA GRANDE with TROYE SIVAN",
      "playCount": 1,
      "spotifyArtistName": "",
      "spotifyTrackName": "",
      "spotifyUri": ""
    },
    {
      "radioStation": "M1",
      "time": "01:00",
      "pageDate": "balandžio 7d.",
      "title": "Bad Dreams",
      "artist": "TEDDY SWIMS",
      "playCount": 1,
      "spotifyArtistName": "",
      "spotifyTrackName": "",
      "spotifyUri": ""
    },
    {
      "radioStation": "M1",
      "time": "00:57",
      "pageDate": "balandžio 7d.",
      "title": "Swim",
      "artist": "BTS",
      "playCount": 1,
      "spotifyArtistName": "",
      "spotifyTrackName": "",
      "spotifyUri": ""
    },
    {
      "radioStation": "M1",
      "time": "00:53",
      "pageDate": "balandžio 7d.",
      "title": "Fotoportretas",
      "artist": "SADBOI",
      "playCount": 1,
      "spotifyArtistName": "",
      "spotifyTrackName": "",
      "spotifyUri": ""
    },
    {
      "radioStation": "M1",
      "time": "00:50",
      "pageDate": "balandžio 7d.",
      "title": "Running",
      "artist": "DOMBRESKY & CHANEY feat. KLP",
      "playCount": 1,
      "spotifyArtistName": "",
      "spotifyTrackName": "",
      "spotifyUri": ""
    },
    {
      "radioStation": "M1",
      "time": "00:47",
      "pageDate": "balandžio 7d.",
      "title": "By Your Side (In My Mind)",
      "artist": "LEONY",
      "playCount": 1,
      "spotifyArtistName": "",
      "spotifyTrackName": "",
      "spotifyUri": ""
    },
    {
      "radioStation": "M1",
      "time": "00:45",
      "pageDate": "balandžio 7d.",
      "title": "Losing My Religion",
      "artist": "MAJESTO x SEALIFE x ALEX D'ROSSO",
      "playCount": 1,
      "spotifyArtistName": "",
      "spotifyTrackName": "",
      "spotifyUri": ""
    },
    {
      "radioStation": "M1",
      "time": "00:42",
      "pageDate": "balandžio 7d.",
      "title": "Camera (CYRIL remix)",
      "artist": "ED SHEERAN",
      "playCount": 1,
      "spotifyArtistName": "",
      "spotifyTrackName": "",
      "spotifyUri": ""
    },
    {
      "radioStation": "M1",
      "time": "00:40",
      "pageDate": "balandžio 7d.",
      "title": "Feelings Back",
      "artist": "OLIVIA ADDAMS",
      "playCount": 1,
      "spotifyArtistName": "",
      "spotifyTrackName": "",
      "spotifyUri": ""
    },
    {
      "radioStation": "M1",
      "time": "00:36",
      "pageDate": "balandžio 7d.",
      "title": "Save My Love",
      "artist": "KYGO, KHALID, GRYFFIN",
      "playCount": 1,
      "spotifyArtistName": "",
      "spotifyTrackName": "",
      "spotifyUri": ""
    },
    {
      "radioStation": "M1",
      "time": "00:33",
      "pageDate": "balandžio 7d.",
      "title": "Talk To Me",
      "artist": "DAMIANO DAVID feat. TYLA, NILE RODGERS",
      "playCount": 1,
      "spotifyArtistName": "",
      "spotifyTrackName": "",
      "spotifyUri": ""
    },
    {
      "radioStation": "M1",
      "time": "00:30",
      "pageDate": "balandžio 7d.",
      "title": "Dega",
      "artist": "KAZIMIERAS LIKSA",
      "playCount": 1,
      "spotifyArtistName": "",
      "spotifyTrackName": "",
      "spotifyUri": ""
    },
    {
      "radioStation": "M1",
      "time": "00:27",
      "pageDate": "balandžio 7d.",
      "title": "Loco Loco",
      "artist": "GORDO & REINIER ZONNEVELD",
      "playCount": 1,
      "spotifyArtistName": "",
      "spotifyTrackName": "",
      "spotifyUri": ""
    },
    {
      "radioStation": "M1",
      "time": "00:24",
      "pageDate": "balandžio 7d.",
      "title": "Friendly Fire",
      "artist": "LINKIN PARK",
      "playCount": 1,
      "spotifyArtistName": "",
      "spotifyTrackName": "",
      "spotifyUri": ""
    },
    {
      "radioStation": "M1",
      "time": "00:21",
      "pageDate": "balandžio 7d.",
      "title": "These Walls",
      "artist": "DUA LIPA feat. PIERRE de MAERE",
      "playCount": 1,
      "spotifyArtistName": "",
      "spotifyTrackName": "",
      "spotifyUri": ""
    },
    {
      "radioStation": "M1",
      "time": "00:18",
      "pageDate": "balandžio 7d.",
      "title": "End Of Beginning",
      "artist": "DJO",
      "playCount": 1,
      "spotifyArtistName": "",
      "spotifyTrackName": "",
      "spotifyUri": ""
    },
    {
      "radioStation": "M1",
      "time": "00:14",
      "pageDate": "balandžio 7d.",
      "title": "Good Feeling",
      "artist": "FLO RIDA",
      "playCount": 1,
      "spotifyArtistName": "",
      "spotifyTrackName": "",
      "spotifyUri": ""
    },
    {
      "radioStation": "M1",
      "time": "00:11",
      "pageDate": "balandžio 7d.",
      "title": "My Loving",
      "artist": "SONNY FODERA & CHRYSTAL",
      "playCount": 1,
      "spotifyArtistName": "",
      "spotifyTrackName": "",
      "spotifyUri": ""
    },
    {
      "radioStation": "M1",
      "time": "00:09",
      "pageDate": "balandžio 7d.",
      "title": "Tyliai Pakuždėk",
      "artist": "JESSICA SHY su NOMBEKO AUGUSTE",
      "playCount": 1,
      "spotifyArtistName": "",
      "spotifyTrackName": "",
      "spotifyUri": ""
    },
    {
      "radioStation": "M1",
      "time": "00:05",
      "pageDate": "balandžio 7d.",
      "title": "Sandstorm",
      "artist": "DARUDE",
      "playCount": 1,
      "spotifyArtistName": "",
      "spotifyTrackName": "",
      "spotifyUri": ""
    },
    {
      "radioStation": "M1",
      "time": "00:02",
      "pageDate": "balandžio 7d.",
      "title": "Revolution",
      "artist": "ALLE FARBEN",
      "playCount": 1,
      "spotifyArtistName": "",
      "spotifyTrackName": "",
      "spotifyUri": ""
    },
    {
      "radioStation": "M1",
      "time": "00:00",
      "pageDate": "balandžio 7d.",
      "title": "No Bad Vibes",
      "artist": "JAZZY & KILIMANJARO",
      "playCount": 1,
      "spotifyArtistName": "",
      "spotifyTrackName": "",
      "spotifyUri": ""
    }
  ]
}
